robotic_arm_package/__init__.py
robotic_arm_package/log_setting.py
robotic_arm_package/robotic_arm.py
robotic_arm_package/libs/linux_arm/libRM_Base.so.1.0.0
robotic_arm_package/libs/linux_x86/libRM_Base.so.1.0.0
robotic_arm_package/libs/win_32/RM_Base.dll
robotic_arm_package/libs/win_64/RM_Base.dll
robotic_arm_package-4.3.6.dist-info/METADATA
robotic_arm_package-4.3.6.dist-info/WHEEL
robotic_arm_package-4.3.6.dist-info/top_level.txt
robotic_arm_package-4.3.6.dist-info/RECORD
