Metadata-Version: 2.1
Name: robotic-arm-package
Version: 4.3.6
Summary: UNKNOWN
Home-page: UNKNOWN
Author: Realman-Aisha
Author-email: aisha@realman-robot.com
License: MIT
Platform: UNKNOWN
Classifier: Programming Language :: Python :: 3
Classifier: License :: OSI Approved :: MIT License
Classifier: Operating System :: OS Independent
